tocaro_client/__init__.py
tocaro_client/tocaro.py
tocaro_client-0.1.1.dist-info/licenses/LICENSE
tocaro_client-0.1.1.dist-info/METADATA
tocaro_client-0.1.1.dist-info/WHEEL
tocaro_client-0.1.1.dist-info/top_level.txt
tocaro_client-0.1.1.dist-info/RECORD
